preset_cli/__init__.py
preset_cli/exceptions.py
preset_cli/lib.py
preset_cli/typing.py
preset_cli/api/__init__.py
preset_cli/api/operators.py
preset_cli/api/clients/__init__.py
preset_cli/api/clients/dbt.py
preset_cli/api/clients/preset.py
preset_cli/api/clients/superset.py
preset_cli/auth/__init__.py
preset_cli/auth/jwt.py
preset_cli/auth/lib.py
preset_cli/auth/main.py
preset_cli/auth/preset.py
preset_cli/auth/superset.py
preset_cli/auth/token.py
preset_cli/cli/__init__.py
preset_cli/cli/export_users.py
preset_cli/cli/main.py
preset_cli/cli/superset/__init__.py
preset_cli/cli/superset/export.py
preset_cli/cli/superset/import_.py
preset_cli/cli/superset/lib.py
preset_cli/cli/superset/main.py
preset_cli/cli/superset/sql.py
preset_cli/cli/superset/sync/__init__.py
preset_cli/cli/superset/sync/main.py
preset_cli/cli/superset/sync/dbt/__init__.py
preset_cli/cli/superset/sync/dbt/command.py
preset_cli/cli/superset/sync/dbt/databases.py
preset_cli/cli/superset/sync/dbt/datasets.py
preset_cli/cli/superset/sync/dbt/exposures.py
preset_cli/cli/superset/sync/dbt/lib.py
preset_cli/cli/superset/sync/dbt/metrics.py
preset_cli/cli/superset/sync/dbt/schemas.py
preset_cli/cli/superset/sync/native/__init__.py
preset_cli/cli/superset/sync/native/command.py
sup/__init__.py
sup/__main__.py
sup/main.py
sup/auth/__init__.py
sup/auth/preset.py
sup/clients/__init__.py
sup/clients/preset.py
sup/clients/superset.py
sup/commands/__init__.py
sup/commands/chart.py
sup/commands/chart_dry.py
sup/commands/config.py
sup/commands/dashboard.py
sup/commands/database.py
sup/commands/dataset.py
sup/commands/dataset_dry.py
sup/commands/query.py
sup/commands/sql.py
sup/commands/sync.py
sup/commands/template_params.py
sup/commands/theme.py
sup/commands/user.py
sup/commands/workspace.py
sup/config/__init__.py
sup/config/paths.py
sup/config/settings.py
sup/config/sync.py
sup/decorators/__init__.py
sup/decorators/filters.py
sup/decorators/output.py
sup/filters/__init__.py
sup/filters/api_params.py
superset_sup-0.1.0.dist-info/licenses/AUTHORS.rst
superset_sup-0.1.0.dist-info/licenses/LICENSE.txt
superset_sup-0.1.0.dist-info/METADATA
superset_sup-0.1.0.dist-info/WHEEL
superset_sup-0.1.0.dist-info/entry_points.txt
superset_sup-0.1.0.dist-info/top_level.txt
superset_sup-0.1.0.dist-info/RECORD
