Metadata-Version: 2.4
Name: superset-sup
Version: 0.1.0
Summary: 'sup - the official Preset CLI with a git-like interface for managing your analytics assets.
Author-email: Beto Dealmeida <beto@preset.io>, Max Beauchemin <max@preset.io>
License: Business Source License 1.1
Project-URL: Homepage, https://github.com/preset-io/superset-sup
Project-URL: Documentation, https://github.com/preset-io/superset-sup/blob/main/README.md
Project-URL: Support, https://preset.io/support
Project-URL: Repository, https://github.com/preset-io/superset-sup
Project-URL: Legacy CLI Documentation, https://github.com/preset-io/preset-cli
Keywords: superset,preset,cli,data,analytics,business-intelligence
Classifier: Development Status :: 4 - Beta
Classifier: Environment :: Console
Classifier: Intended Audience :: Developers
Classifier: Intended Audience :: System Administrators
Classifier: Programming Language :: Python
Classifier: Programming Language :: Python :: 3.8
Classifier: Programming Language :: Python :: 3.9
Classifier: Programming Language :: Python :: 3.10
Classifier: Programming Language :: Python :: 3.11
Classifier: Topic :: Database
Classifier: Topic :: Software Development :: Libraries :: Python Modules
Classifier: Topic :: System :: Systems Administration
Classifier: License :: Other/Proprietary License
Requires-Python: >=3.8
License-File: LICENSE.txt
License-File: AUTHORS.rst
Requires-Dist: importlib-metadata; python_version < "3.8"
Requires-Dist: Cython>=0.29.26
Requires-Dist: PyYAML>=6.0
Requires-Dist: appdirs>=1.4.4
Requires-Dist: backoff>=1.10.0
Requires-Dist: beautifulsoup4>=4.10.0
Requires-Dist: click>=8.1.2
Requires-Dist: jinja2>=3.0.3
Requires-Dist: marshmallow>=3.17.0
Requires-Dist: numpy>=1.21.5
Requires-Dist: pandas>=1.3.5
Requires-Dist: prison>=0.2.1
Requires-Dist: prompt-toolkit>=3.0.24
Requires-Dist: pygments>=2.11.2
Requires-Dist: python-graphql-client>=0.4.3
Requires-Dist: requests>=2.26.0
Requires-Dist: rich>=12.3.0
Requires-Dist: sqlalchemy<2,>=1.4
Requires-Dist: sqlglot>=26
Requires-Dist: tabulate>=0.8.9
Requires-Dist: typing-extensions>=4.0.1
Requires-Dist: yarl>=1.7.2
Requires-Dist: greenlet>=1.1.3
Requires-Dist: aiohttp>=3.8.3
Requires-Dist: typer>=0.12.0
Requires-Dist: pydantic>=2.0.0
Requires-Dist: pydantic-settings>=2.0.0
Requires-Dist: halo>=0.0.31
Provides-Extra: snowflake
Requires-Dist: snowflake-sqlalchemy==1.4.4; extra == "snowflake"
Provides-Extra: testing
Requires-Dist: setuptools; extra == "testing"
Requires-Dist: freezegun; extra == "testing"
Requires-Dist: pytest; extra == "testing"
Requires-Dist: pytest-cov; extra == "testing"
Requires-Dist: pytest-mock; extra == "testing"
Requires-Dist: pyfakefs; extra == "testing"
Requires-Dist: requests-mock; extra == "testing"
Requires-Dist: codespell; extra == "testing"
Requires-Dist: pre-commit; extra == "testing"
Requires-Dist: pip-tools>=6.6.0; extra == "testing"
Requires-Dist: ruff>=0.8.0; extra == "testing"
Dynamic: license-file
